{"py/object": "rasa.core.featurizers.tracker_featurizers.IntentMaxHistoryTrackerFeaturizer", "state_featurizer": {"py/object": "rasa.core.featurizers.single_state_featurizer.IntentTokenizerSingleStateFeaturizer", "_default_feature_states": {"intent": {"ask_tmi": 0, "back": 1, "bot_challenge": 2, "goodbye": 3, "greet": 4, "nlu_fallback": 5, "out_of_scope": 6, "prove_human": 7, "provide_artist": 8, "provide_feeling": 9, "provide_genre": 10, "provide_lyric": 11, "provide_title": 12, "restart": 13, "session_start": 14, "share_music": 15, "specify_artist": 16, "specify_feeling": 17, "specify_genre": 18, "specify_lyric": 19, "swear": 20}, "action_name": {"action_listen": 0, "action_restart": 1, "action_session_start": 2, "action_default_fallback": 3, "action_deactivate_loop": 4, "action_revert_fallback_events": 5, "action_default_ask_affirmation": 6, "action_default_ask_rephrase": 7, "action_two_stage_fallback": 8, "action_unlikely_intent": 9, "action_back": 10, "...": 11, "action_extract_slots": 12, "utter_greet": 13, "action_recommend_music_by_genre": 14, "action_recommend_music_by_artist": 15, "action_recommend_music_by_lyric": 16, "action_recommend_music_by_feeling": 17, "utter_bot_challenge": 18, "utter_ask_genre": 19, "utter_ask_artitst": 20, "utter_ask_title": 21, "utter_ask_lyric": 22, "utter_ask_feeling": 23, "action_save_music": 24, "utter_ask_tmi": 25, "utter_prove_human": 26, "utter_swear": 27, "utter_goodbye": 28, "utter_ask_artist": 29}, "entities": {"artist": 0, "feeling": 1, "genre": 2, "lyric": 3, "title": 4}, "slots": {"genre_0": 0, "artist_0": 1, "lyric_0": 2, "feeling_0": 3, "title_0": 4}, "active_loop": {}}, "action_texts": [], "entity_tag_specs": []}, "max_history": 5, "remove_duplicates": true}